MANIFEST.in
README.md
setup.cfg
setup.py
cdtw/__init__.py
cdtw/cdtw.c
cdtw/cdtw.h
cdtw/cydtw.c
cdtw/cydtw.pyx
cdtw/examples.ipynb
cdtw/pydtw.py
cdtw/stepstr.py
cdtw.egg-info/PKG-INFO
cdtw.egg-info/SOURCES.txt
cdtw.egg-info/dependency_links.txt
cdtw.egg-info/requires.txt
cdtw.egg-info/top_level.txt
cdtw/test/__init__.py
cdtw/test/test.py