Metadata-Version: 1.0
Name: cdtw
Version: 0.0.1
Summary: DTW computation
Home-page: https://github.com/honeyext/cdtw
Author: Aliaksei Halachkin
Author-email: aliaksei.h(you know what)gmail.com
License: UNKNOWN
Keywords: dtw,dynamic time warping
Platform: UNKNOWN
